LICENSE.md
README.md
setup.cfg
setup.py
wikileaf/__init__.py
wikileaf/constants.py
wikileaf/core.py
wikileaf/models.py
wikileaf/utils.py
wikileaf.egg-info/PKG-INFO
wikileaf.egg-info/SOURCES.txt
wikileaf.egg-info/dependency_links.txt
wikileaf.egg-info/requires.txt
wikileaf.egg-info/top_level.txt